{"stem":"0026","instances":[{"docId":"amp-transcript__0038","docUri":"amp-transcript__0038.html","score":0.0065435901548680404,"contexts":[{"form":"0026","weight":"1","pos":98,"context":"...they,though,ever (vl) 0025Take you in,who to Goebbels' (vl) <mark>0026<\/mark>Offer of culture (vl) 0027Countered In Ruah lassen...","fid":"transcription__lg3__vl26"},{"form":"0026","weight":"1","pos":408,"context":"...my effort to do my 0025  Gemeindepflicht. <mark>0026<\/mark>                  love 0027 Wystan. ","fid":"transcription__p8__lb26"}]},{"docId":"amp-transcript__0039","docUri":"amp-transcript__0039.html","score":0.0047174719721141695,"contexts":[{"form":"0026","weight":"1","pos":92,"context":"...long,though, (vl) 0025Take you in,who to Goebbells' (vl) <mark>0026<\/mark>Offer of culture (vl) 0027Countered In Ruah lassen...","fid":"transcription__lg3__vl26"},{"form":"0026","weight":"1","pos":142,"context":" <mark>0026<\/mark>                           JOSEPH WEINHEBER 0027                             (I892-I945)...","fid":"transcription__p8__lb26"}]},{"docId":"amp-transcript__0062","docUri":"amp-transcript__0062.html","score":0.000508611687758235,"contexts":[{"form":"0026","weight":"1","pos":130,"context":"...risk of slithering off the path to the right. <mark>0026<\/mark>      On walking through the wicket-gate next to...","fid":"transcription__p1__lb26"},{"form":"0026","weight":"1","pos":3061,"context":"...(vl) 0025SYou are unlikely to encounter        (vl) <mark>0026<\/mark>Dragons or romance:  were drama a craving,...","fid":"transcription__lg5__vl26"}]},{"docId":"amp-transcript__0018","docUri":"amp-transcript__0018.html","score":0.009082893797055638,"contexts":[{"form":"0026","weight":"1","pos":70,"context":"...Return to New York on NOv 1st. 0025 love <mark>0026<\/mark> Wystan ","fid":"transcription__p6__lb26"},{"form":"0026","weight":"1","pos":168,"context":"...must (vl) 0025so disarray the heavens, (vl) <mark>0026<\/mark>at least you might let them rain. (vl)...","fid":"transcription__lg2__vl26"}]},{"docId":"amp-transcript__0013","docUri":"amp-transcript__0013.html","score":0.012547502771190265,"contexts":[{"form":"0026","weight":"1","pos":63,"context":"...of the car. No answer from Holfman. <mark>0026<\/mark> Can he be dead, too? I should be...","fid":"transcription__p8__lb26"}]},{"docId":"amp-transcript__0011","docUri":"amp-transcript__0011.html","score":0.014842777668359217,"contexts":[{"form":"0026","weight":"1","pos":69,"context":"...Chester is going to Vienna,but he was too <mark>0026<\/mark> upset for []me to find out where he would...","fid":"transcription__p8__lb26"}]},{"docId":"amp-transcript__0028","docUri":"amp-transcript__0028.html","score":0.0006238379132780399,"contexts":[{"form":"0026","weight":"1","pos":119,"context":"...on record which would otherwise be lost.  Not <mark>0026<\/mark> for the first time self.-criticism was expressed,...","fid":"transcription__p1__lb26"}]},{"docId":"amp-transcript__0053","docUri":"amp-transcript__0053.html","score":0.0017412128309090926,"contexts":[{"form":"0026","weight":"1","pos":228,"context":"....  Hatte er also die verdorbenen deutschen und <mark>0026<\/mark> italienischen Sprachen illustriert, so ging er später auf...","fid":"transcription__p2__lb26"}]},{"docId":"amp-transcript__0008","docUri":"amp-transcript__0008.html","score":0.01714236294092191,"contexts":[{"form":"0026","weight":"1","pos":68,"context":"...to Fridau 0025 and air-mail to me <mark>0026<\/mark> ℅ Mr Peter Heyworth 0027 32 Bryanston Square 0028...","fid":"transcription__p7__lb26"}]},{"docId":"amp-transcript__0052","docUri":"amp-transcript__0052.html","score":0.002419697353489972,"contexts":[{"form":"0026","weight":"1","pos":210,"context":"...werden'? Bevor er mir zuerkannt wurde, hatte <mark>0026<\/mark> ich noch nie von diesem Preis gehört. Es...","fid":"transcription__p2__lb26"}]},{"docId":"amp-transcript__0051","docUri":"amp-transcript__0051.html","score":0.004196923340708468,"contexts":[{"form":"0026","weight":"1","pos":218,"context":" <mark>0026<\/mark> Einschub 4 0027        Eine eigene Phantasiewelt für sich...","fid":"transcription__p4__lb26"}]},{"docId":"amp-transcript__0056","docUri":"amp-transcript__0056.html","score":0.01995258637385993,"contexts":[{"form":"0026","weight":"1","pos":72,"context":"...Incident of \"he whose name we never mention' at <mark>0026<\/mark> funeral. ? Repetition of mention of this on...","fid":"transcription__p9__lb26"}]},{"docId":"amp-transcript__0027","docUri":"amp-transcript__0027.html","score":0.0012811660724267948,"contexts":[{"form":"0026","weight":"1","pos":76,"context":"...of poetry,or at least about the kind I <mark>0026<\/mark> am interested in writing,I discovered long before I...","fid":"transcription__p8__lb26"}]},{"docId":"amp-transcript__0006","docUri":"amp-transcript__0006.html","score":0.017639243026166023,"contexts":[{"form":"0026","weight":"1","pos":62,"context":"...a 0025 prospective couple to take the Eiermanns place. <mark>0026<\/mark> Expect to be staying at the Hotel 0027 Königin...","fid":"transcription__p8__lb26"}]},{"docId":"amp-transcript__0014","docUri":"amp-transcript__0014.html","score":0.021734067300097422,"contexts":[{"form":"0026","weight":"1","pos":64,"context":"...hear about the 0024 Royal vsit. 0025 love <mark>0026<\/mark> Wystan' ","fid":"transcription__p8__lb26"}]},{"docId":"amp-transcript__0001","docUri":"amp-transcript__0001.html","score":0.01789864365890376,"contexts":[{"form":"0026","weight":"1","pos":65,"context":"...you to-morrow to arrange 0025 a meeting. <mark>0026<\/mark> Chester is at the moment in Florence,but 0027...","fid":"transcription__p8__lb26"}]},{"docId":"amp-transcript__0032","docUri":"amp-transcript__0032.html","score":0.007201821117192045,"contexts":[{"form":"0026","weight":"1","pos":104,"context":" <mark>0026<\/mark> I still think your piece is first-rate (the...","fid":"transcription__p5__lb26"}]},{"docId":"amp-transcript__0030","docUri":"amp-transcript__0030.html","score":0.008393846681416935,"contexts":[{"form":"0026","weight":"1","pos":99,"context":"...the right bell.  Then there was the burial <mark>0026<\/mark> service. I am told that the whole occasion...","fid":"transcription__p6__lb26"}]},{"docId":"amp-transcript__0002","docUri":"amp-transcript__0002.html","score":0.010676383936889964,"contexts":[{"form":"0026","weight":"1","pos":69,"context":"...are so much nicer under a little Druck. <mark>0026<\/mark> When they feel their oats they are so apt...","fid":"transcription__p8__lb26"}]},{"docId":"amp-transcript__0012","docUri":"amp-transcript__0012.html","score":0.01580659440007085,"contexts":[{"form":"0026","weight":"1","pos":70,"context":"...Holfmann to see if 0025 he knows anything . <mark>0026<\/mark> Adress. Wien VII, Schweighofergasse 4\/21 0027 Tel...","fid":"transcription__p7__lb26"}]},{"docId":"amp-transcript__0005","docUri":"amp-transcript__0005.html","score":0.014663949021752477,"contexts":[{"form":"0026","weight":"1","pos":76,"context":"...Wien , could you be a dear and stop <mark>0026<\/mark> in Kirchstetten to see what is happening. 0027...","fid":"transcription__p7__lb26"}]},{"docId":"amp-transcript__0029","docUri":"amp-transcript__0029.html","score":0.006837684094412673,"contexts":[{"form":"0026","weight":"1","pos":77,"context":"...mescalin, 0025 Point is that young people need <mark>0026<\/mark> to discover who &amp; what they are .- ","fid":"transcription__p2__lb26"}]},{"docId":"amp-transcript__0031","docUri":"amp-transcript__0031.html","score":0.0031613188800141702,"contexts":[{"form":"0026","weight":"1","pos":99,"context":"...be said by us, who knew Auden in Kirchstetten <mark>0026<\/mark> in view of the fact that Carpenter did no...","fid":"transcription__p4__lb26"}]},{"docId":"amp-transcript__0033","docUri":"amp-transcript__0033.html","score":0.004645449499257465,"contexts":[{"form":"0026","weight":"1","pos":122,"context":"...sound very attractive.  (Which publisher is interested?)  The <mark>0026<\/mark> place to write for permissions is to the agents...","fid":"transcription__p6__lb26"}]},{"docId":"amp-transcript__0015","docUri":"amp-transcript__0015.html","score":0.018165787594111277,"contexts":[{"form":"0026","weight":"1","pos":62,"context":"...lunch at 12·0, 0025 Could you possibly make that? <mark>0026<\/mark> If not,perhaps you could come 0027 on Monday,if...","fid":"transcription__p7__lb26"}]},{"docId":"amp-transcript__0042","docUri":"amp-transcript__0042.html","score":0.005071282370022732,"contexts":[{"form":"0026","weight":"1","pos":129,"context":"...were, (vl) 0025Ssurely you should have foreseen (vl) <mark>0026<\/mark>the doom that your death (vl) 0027would spell...","fid":"transcription__lg2__vl26"}]},{"docId":"amp-transcript__0041","docUri":"amp-transcript__0041.html","score":0.009895185112239475,"contexts":[{"form":"0026","weight":"1","pos":67,"context":"...instructed. My! how erudite you are, Where did <mark>0026<\/mark> you dig up all those stories ? 0027 A...","fid":"transcription__p10__lb26"}]},{"docId":"amp-transcript__0046","docUri":"amp-transcript__0046.html","score":0.007559675582642581,"contexts":[{"form":"0026","weight":"1","pos":108,"context":" <mark>0026<\/mark> 11. Bedeutenderern Nachbarn 0027 Warum des noblen Flusses ?...","fid":"transcription__p10__lb26"}]},{"docId":"amp-transcript__0003","docUri":"amp-transcript__0003.html","score":0.013523419653393952,"contexts":[{"form":"0026","weight":"1","pos":60,"context":" <mark>0026<\/mark> Dear Stella: 0027 Many thanks for your letter...","fid":"transcription__p11__lb26"}]},{"docId":"amp-transcript__0004","docUri":"amp-transcript__0004.html","score":0.006405830362133977,"contexts":[{"form":"0026","weight":"1","pos":82,"context":"..., 0025         Moxzart,et al,had never existed. <mark>0026<\/mark>     2) I believe that the only way in which,...","fid":"transcription__p6__lb26"}]},{"docId":"amp-transcript__0020","docUri":"amp-transcript__0020.html","score":0.02135276787377992,"contexts":[{"form":"0026","weight":"1","pos":61,"context":"...at the Hotel Altburg[]hof 0025 Altburgenhof, <mark>0026<\/mark> love 0027 Wystan, ","fid":"transcription__p7__lb26"}]},{"docId":"amp-transcript__0043","docUri":"amp-transcript__0043.html","score":0.0013553538628123117,"contexts":[{"form":"0026","weight":"1","pos":92,"context":"...of poetry,or at least about the kind I <mark>0026<\/mark> am interested in writing,I discovered long before I...","fid":"transcription__p5__lb26"}]},{"docId":"amp-transcript__0009","docUri":"amp-transcript__0009.html","score":0.010964934854103204,"contexts":[{"form":"0026","weight":"1","pos":67,"context":"...they be able to find work or emigrate before <mark>0026<\/mark> I return in April,when I'm afraid there will...","fid":"transcription__p8__lb26"}]},{"docId":"amp-transcript__0034","docUri":"amp-transcript__0034.html","score":0.007117589291259974,"contexts":[{"form":"0026","weight":"1","pos":116,"context":"...1937 portrait, a portrait by Mervyn Peake painted <mark>0026<\/mark> in the same year, two drawings by Maurice Field...","fid":"transcription__p8__lb26"}]},{"docId":"amp-transcript__0047","docUri":"amp-transcript__0047.html","score":0.0029541450699161536,"contexts":[{"form":"0026","weight":"1","pos":215,"context":"...der vom Albdruck erstarrt, dich selbst vernichtetest? <mark>0026<\/mark> Vergeltung ging immer wie ein Stümper vor.  ...","fid":"transcription__p1__lb26"}]}]}