{"stem":"0051","instances":[{"docId":"amp-transcript__0028","docUri":"amp-transcript__0028.html","score":0.0003706323342146275,"contexts":[{"form":"0051","weight":"1","pos":235,"context":"....  As a staritting point, \"Early Auden\"1 which <mark>0051<\/mark> presents ansd comments on the poetry, drama and...","fid":"transcription__p4__lb51"}]},{"docId":"amp-transcript__0053","docUri":"amp-transcript__0053.html","score":0.001034483095926664,"contexts":[{"form":"0051","weight":"1","pos":468,"context":"...da ein bißl - im soziologisch-biologischen Sinne <mark>0051<\/mark> artfremd.  Aber nicht nur in Österreich:...","fid":"transcription__p3__lb51"}]},{"docId":"amp-transcript__0039","docUri":"amp-transcript__0039.html","score":0.0014013637287843763,"contexts":[{"form":"0051","weight":"1","pos":316,"context":"...solltest,der kommen muusste,eine Zeit, <mark>0051<\/mark> voller Schrecken,Tränen und Auflösung,in sdem du,...","fid":"transcription__p18__lb51"}]},{"docId":"amp-transcript__0062","docUri":"amp-transcript__0062.html","score":0.00015096110314253403,"contexts":[{"form":"0051","weight":"1","pos":281,"context":"...:  the content was all, the package irrelevant. <mark>0051<\/mark> Here lie, precariously balanced, collapsing, upended...","fid":"transcription__p3__lb51"}]},{"docId":"amp-transcript__0052","docUri":"amp-transcript__0052.html","score":0.00143758187684441,"contexts":[{"form":"0051","weight":"1","pos":421,"context":"...seiner Muttersprache hegt , und zweitens davon, was <mark>0051<\/mark>         nach dem Krieg in den Ländern geschehen ist...","fid":"transcription__p4__lb51"}]},{"docId":"amp-transcript__0051","docUri":"amp-transcript__0051.html","score":0.0024934609794922007,"contexts":[{"form":"0051","weight":"1","pos":370,"context":"...der er angehört, wie an ihrer Verbesserung , <mark>0051<\/mark>      mitzuwirken . \" ","fid":"transcription__p11__lb51"}]},{"docId":"amp-transcript__0027","docUri":"amp-transcript__0027.html","score":0.0007611617726870925,"contexts":[{"form":"0051","weight":"1","pos":211,"context":"...     Secondly,in constructing my private world,I discoveresd that,though this was <mark>0051<\/mark> a game,or rather precisely because it was a...","fid":"transcription__p8__lb51"}]},{"docId":"amp-transcript__0032","docUri":"amp-transcript__0032.html","score":0.004278720023980699,"contexts":[{"form":"0051","weight":"1","pos":190,"context":"...Musulin 0049                                          Schlösselgasse 8\/17 0050                                          A-1080 Wien <mark>0051<\/mark>                                          Austria ","fid":"transcription__p11__lb51"}]},{"docId":"amp-transcript__0029","docUri":"amp-transcript__0029.html","score":0.004062380247487294,"contexts":[{"form":"0051","weight":"1","pos":150,"context":" <mark>0051<\/mark> 2 ","fid":"transcription__p4__lb51"}]},{"docId":"amp-transcript__0031","docUri":"amp-transcript__0031.html","score":0.001878191387149969,"contexts":[{"form":"0051","weight":"1","pos":204,"context":"...Auden held at Neulengbach.  I have the original <mark>0051<\/mark> English text which to my horror Auden asked me...","fid":"transcription__p6__lb51"}]},{"docId":"amp-transcript__0033","docUri":"amp-transcript__0033.html","score":0.00275993772539213,"contexts":[{"form":"0051","weight":"1","pos":222,"context":"..., talthough we may put off the southern trip <mark>0051<\/mark> for another year or so.  I haven't been across...","fid":"transcription__p8__lb51"}]},{"docId":"amp-transcript__0004","docUri":"amp-transcript__0004.html","score":0.003805808863435464,"contexts":[{"form":"0051","weight":"1","pos":207,"context":"...love and greetings to son and mum-in-law <mark>0051<\/mark> Wystan. ","fid":"transcription__p6__lb51"}]},{"docId":"amp-transcript__0043","docUri":"amp-transcript__0043.html","score":0.0008052379555152987,"contexts":[{"form":"0051","weight":"1","pos":227,"context":"...     Secondly,in constructing my private world,I discoveresd that,though this was <mark>0051<\/mark> a game,or rather precisely because it was a...","fid":"transcription__p5__lb51"}]},{"docId":"amp-transcript__0047","docUri":"amp-transcript__0047.html","score":0.0017551060292542184,"contexts":[{"form":"0051","weight":"1","pos":449,"context":"...Regime, das sie kennen, von des April <mark>0051<\/mark> rasch zunehmenden Farbtönen bis zum ungestümen Herbst, wenn...","fid":"transcription__p1__lb51"}]}]}