{"stem":"0064","instances":[{"docId":"amp-transcript__0062","docUri":"amp-transcript__0062.html","score":0.0006749050470027138,"contexts":[{"form":"0064","weight":"1","pos":357,"context":"...Dictionary, all thirteen volumes of it, at each <mark>0064<\/mark> of ones residences?  \"Of courxse\" said Auden,...","fid":"transcription__p3__lb64"},{"form":"0064","weight":"1","pos":7360,"context":"...            (vl) 0063they know, from April's             (vl) <mark>0064<\/mark>rapid augment of colour             (vl) 0065till boisterous...","fid":"transcription__lg12__vl64"}]},{"docId":"amp-transcript__0028","docUri":"amp-transcript__0028.html","score":0.0008278051140325442,"contexts":[{"form":"0064","weight":"1","pos":309,"context":"...difference at all.\"  Chester´s sole explanatio[] <mark>0064<\/mark> was that it was \"a tick like any other\",...","fid":"transcription__p4__lb64"}]},{"docId":"amp-transcript__0038","docUri":"amp-transcript__0038.html","score":0.004341526283541649,"contexts":[{"form":"0064","weight":"1","pos":211,"context":"...warm (vl) 0063And over-eating,their crimes (vl) <mark>0064<\/mark>The pedestrian (vl) 0065Private sort,those nuisances,...","fid":"transcription__lg7__vl64"}]},{"docId":"amp-transcript__0053","docUri":"amp-transcript__0053.html","score":0.002310511841884826,"contexts":[{"form":"0064","weight":"1","pos":584,"context":"......  Mein Leben lang ringe ich mit dem <mark>0064<\/mark> Tod, kämpfe ich gegen Selbstmordgedanken... Ich bin...","fid":"transcription__p4__lb64"}]},{"docId":"amp-transcript__0039","docUri":"amp-transcript__0039.html","score":0.003129937553250956,"contexts":[{"form":"0064","weight":"1","pos":462,"context":"...für ihre Geschändeten verblallasste der Schock,ihre gewaltsam <mark>0064<\/mark> entführten Physiker hatten kein Heimwheh mehr. 0065 ","fid":"transcription__p22__lb64"}]},{"docId":"amp-transcript__0052","docUri":"amp-transcript__0052.html","score":0.0032108305715258323,"contexts":[{"form":"0064","weight":"1","pos":528,"context":"..., wenn er erfolgreich ist, mit seinen Büchern <mark>0064<\/mark>            eine Menge Geld verdienen. Ein Lyriker kann...","fid":"transcription__p6__lb64"}]},{"docId":"amp-transcript__0027","docUri":"amp-transcript__0027.html","score":0.0017000502920815712,"contexts":[{"form":"0064","weight":"1","pos":284,"context":"...particuallar lead-mining world,I decided,or rather,without conscious <mark>0064<\/mark> decision I instinctively felt,that I must impose two restrictions...","fid":"transcription__p10__lb64"}]},{"docId":"amp-transcript__0029","docUri":"amp-transcript__0029.html","score":0.009073302120660076,"contexts":[{"form":"0064","weight":"1","pos":184,"context":"...you do meet someone 0063 interesting your'e torn apart <mark>0064<\/mark> after 2 or 3 minutes, 0065 W. had...","fid":"transcription__p5__lb64"}]},{"docId":"amp-transcript__0018","docUri":"amp-transcript__0018.html","score":0.006026297677154827,"contexts":[{"form":"0064","weight":"1","pos":285,"context":"...0063ken at first hand what's cooking.) (vl) <mark>0064<\/mark>Have done! What good does it do, (vl) 0065...","fid":"transcription__lg5__vl64"}]},{"docId":"amp-transcript__0031","docUri":"amp-transcript__0031.html","score":0.0041949292921493325,"contexts":[{"form":"0064","weight":"1","pos":261,"context":"...waking hours in the fabrication of a private secondary <mark>0064<\/mark> s   sacred world, the basic elements of which...","fid":"transcription__p8__lb64"}]},{"docId":"amp-transcript__0033","docUri":"amp-transcript__0033.html","score":0.006164304494188906,"contexts":[{"form":"0064","weight":"1","pos":256,"context":"...                                    Sch[]ltösselgasse 8\/17 0063                                     A-1080 Vienna <mark>0064<\/mark>                                     Austria ","fid":"transcription__p11__lb64"}]},{"docId":"amp-transcript__0042","docUri":"amp-transcript__0042.html","score":0.006729365739489556,"contexts":[{"form":"0064","weight":"1","pos":233,"context":"...you would treat us to the sulks. (vl) <mark>0064<\/mark>But when in good form, (vl) 0065how...","fid":"transcription__lg3__vl64"}]},{"docId":"amp-transcript__0043","docUri":"amp-transcript__0043.html","score":0.0017984941842733781,"contexts":[{"form":"0064","weight":"1","pos":322,"context":"...a manufacturer's catalogue: but I was not free <mark>0064<\/mark> to invent one.  In deciding how my world was...","fid":"transcription__p6__lb64"}]},{"docId":"amp-transcript__0047","docUri":"amp-transcript__0047.html","score":0.003920018877372556,"contexts":[{"form":"0064","weight":"1","pos":555,"context":"...die Violas zu hören, die ihn nachher dazu <mark>0064<\/mark> verpflichteten, sie \"den Abgrund zu nennen\". ","fid":"transcription__p3__lb64"}]}]}