{"stem":"0113","instances":[{"docId":"amp-transcript__0053","docUri":"amp-transcript__0053.html","score":0.0016886893440042677,"contexts":[{"form":"0113","weight":"1","pos":1082,"context":"...Haut im Augenblick kin keinem guten Zustand ist, <mark>0113<\/mark> ist sehr ärgerlich und ich frage mich, was...","fid":"transcription__p3__lb113"}]},{"docId":"amp-transcript__0043","docUri":"amp-transcript__0043.html","score":0.001335915200222554,"contexts":[{"form":"0113","weight":"1","pos":620,"context":"...their artistic merits,Palestrina must have lived earlier <mark>0113<\/mark> than Mozart: he could not possibly have written...","fid":"transcription__p10__lb113"}]},{"docId":"amp-transcript__0027","docUri":"amp-transcript__0027.html","score":0.0012902554745258623,"contexts":[{"form":"0113","weight":"1","pos":588,"context":" Why is this passage <mark>0113<\/mark> underlined ? ","fid":"transcription__p19__lb113"}]},{"docId":"amp-transcript__0028","docUri":"amp-transcript__0028.html","score":0.0006152795559384632,"contexts":[{"form":"0113","weight":"1","pos":566,"context":"...yore speaking to the \"boy\", and when I <mark>0113<\/mark> asked one day at lucnch: \"Where is, er....?\"...","fid":"transcription__p7__lb113"}]},{"docId":"amp-transcript__0062","docUri":"amp-transcript__0062.html","score":0.0002515609878321057,"contexts":[{"form":"0113","weight":"1","pos":623,"context":"...with their children Arabella and Octavian.  There was <mark>0113<\/mark> a constant coming and going between Prilelau and the...","fid":"transcription__p7__lb113"}]}]}