{"stem":"0308","instances":[{"docId":"amp-transcript__0028","docUri":"amp-transcript__0028.html","score":0.0008245014322118792,"contexts":[{"form":"0308","weight":"1","pos":1484,"context":"...have 0307           received the money, not I. <mark>0308<\/mark>           2.  I believe you are not clearly aware how...","fid":"transcription__p32__lb308"}]},{"docId":"amp-transcript__0062","docUri":"amp-transcript__0062.html","score":0.0003371026921898092,"contexts":[{"form":"0308","weight":"1","pos":1644,"context":"..., over the good air, the clear view <mark>0308<\/mark> after the storm of two days ago.  I was...","fid":"transcription__p18__lb308"}]}]}