{"stem":"admir","instances":[{"docId":"amp-transcript__0062","docUri":"amp-transcript__0062.html","score":0.0018542929936880637,"contexts":[{"form":"admiration","weight":"1","pos":1081,"context":"...?  Do they like to congregate together for mutual <mark>admiration<\/mark> and to complain about their publishers?  At some...","fid":"text-resize-13"},{"form":"admiring","weight":"1","pos":2789,"context":"...was at last able to extract him from the <mark>admiring<\/mark> group and take him out to my car....","fid":"text-resize-39"},{"form":"admired","weight":"1","pos":5033,"context":"...tones of the British county gentry, he intensely <mark>admired<\/mark> \"Akenfield\", he loved the Lucia novels by E.F....","fid":"text-resize-71"},{"form":"admired","weight":"1","pos":5245,"context":"...is silence) is comically....  I have enormously <mark>admired<\/mark> - and by been influenced by - the tradition...","fid":"text-resize-73"}]},{"docId":"amp-transcript__0004","docUri":"amp-transcript__0004.html","score":0.010015183201520244,"contexts":[{"form":"admired","weight":"1","pos":73,"context":"...find this hard to accept. I have enormously <mark>admired<\/mark> - and been       influenced by - the tradition...","fid":"text-resize-3"}]},{"docId":"amp-transcript__0041","docUri":"amp-transcript__0041.html","score":0.017621651455839417,"contexts":[{"form":"admiration","weight":"1","pos":86,"context":"...forward to seeing you in Sept[] love and <mark>admiration<\/mark> Wystan ","fid":"text-resize-3"}]}]}