{"stem":"aethet","instances":[{"docId":"amp-transcript__0043","docUri":"amp-transcript__0043.html","score":0.0027584869206232327,"contexts":[{"form":"aethetic","weight":"1","pos":380,"context":"...was my 0073  moral duty to sacrifice my <mark>aethetic<\/mark> aesthetic preference to reality or truth. ","fid":"text-resize-3"}]},{"docId":"amp-transcript__0027","docUri":"amp-transcript__0027.html","score":0.0026047542110616863,"contexts":[{"form":"aethetic","weight":"1","pos":373,"context":"...was my 0078  moral duty to sacrifice my <mark>aethetic<\/mark> aesthetic preference to reality or truth. ","fid":"text-resize-1"}]}]}