{"stem":"believ","instances":[{"docId":"amp-transcript__0062","docUri":"amp-transcript__0062.html","score":0.0008171786726588651,"contexts":[{"form":"believed","weight":"1","pos":4571,"context":"...the telephone line line from Athens, but he <mark>believed<\/mark> that he must be in 0876 Vienna.  Would...","fid":"text-resize-51"},{"form":"believes","weight":"1","pos":5249,"context":"...one must be convinced that the poet really 1008 <mark>believes<\/mark> what he says, however odd the belief may seem...","fid":"text-resize-59"},{"form":"believing","weight":"1","pos":7215,"context":"...     But then worry invaded it.  While all the time <mark>believing<\/mark> 1406 himself not to be liable for income tax...","fid":"text-resize-83"}]},{"docId":"amp-transcript__0028","docUri":"amp-transcript__0028.html","score":0.0013324623852818236,"contexts":[{"form":"believed","weight":"1","pos":2092,"context":"...spoke.  The 0439 inhabitants of Kirchstetten, she <mark>believed<\/mark>, would hardly bury a dog 0440 in the...","fid":"text-resize-27"},{"form":"believer","weight":"1","pos":2111,"context":"...him, an EAmerican of Jewish origin and a non-<mark>believer<\/mark>, 0443 the whole pomp and circumstance of a...","fid":"text-resize-27"}]},{"docId":"amp-transcript__0043","docUri":"amp-transcript__0043.html","score":0.0014465430689532119,"contexts":[{"form":"believ","weight":"1","pos":408,"context":"...one must 0073 nbe convinced that the poet really <mark>believ<\/mark>[]es what he says,however odd that the 0074 belief...","fid":"text-resize-5"}]},{"docId":"amp-transcript__0027","docUri":"amp-transcript__0027.html","score":0.0013971022363870047,"contexts":[{"form":"believ","weight":"1","pos":397,"context":"...one must 0074 nbe convinced that the poet really <mark>believ<\/mark>[]es what he says,however odd that the 0075 belief...","fid":"text-resize-3"}]}]}