{"stem":"cart","instances":[{"docId":"amp-transcript__0038","docUri":"amp-transcript__0038.html","score":0.0055807890536191986,"contexts":[{"form":"carted","weight":"1","pos":155,"context":"...sort,those nuisances, Corpses and rubble, Lonfg <mark>carted<\/mark> away: for their raped The shock was fading,...","fid":"text-resize-5"}]},{"docId":"amp-transcript__0062","docUri":"amp-transcript__0062.html","score":0.00032739075659018676,"contexts":[{"form":"cart","weight":"1","pos":106,"context":"...and anyway became a habit, to take the <mark>cart<\/mark> track 0022  through the field with its ruts,...","fid":"text-resize-1"}]}]}