{"stem":"chose","instances":[{"docId":"amp-transcript__0062","docUri":"amp-transcript__0062.html","score":0.0008439372150536222,"contexts":[{"form":"chose","weight":"1","pos":4094,"context":"...I was free to do or not as a <mark>chose<\/mark> - it could not be played without rules....","fid":"text-resize-57"},{"form":"chose","weight":"1","pos":4903,"context":"...is immaterial, it is still surprising that heAuden <mark>chose<\/mark> to repeat it in Neulengbach.  If here and...","fid":"text-resize-69"}]},{"docId":"amp-transcript__0031","docUri":"amp-transcript__0031.html","score":0.004607897194192777,"contexts":[{"form":"chose","weight":"1","pos":245,"context":"...see what it´s about. I cannot believe that Wystan <mark>chose<\/mark> Neulengbach to make a one-time-only statement of...","fid":"text-resize-3"}]},{"docId":"amp-transcript__0043","docUri":"amp-transcript__0043.html","score":0.0019615661430387207,"contexts":[{"form":"chose","weight":"1","pos":183,"context":"...I was free to do or not as I <mark>chose<\/mark> - it could not be played without rules....","fid":"text-resize-3"}]},{"docId":"amp-transcript__0027","docUri":"amp-transcript__0027.html","score":0.0019346133258061273,"contexts":[{"form":"chose","weight":"1","pos":167,"context":"...I was free to do or not as I <mark>chose<\/mark> - it could not be played without rules....","fid":"text-resize-1"}]}]}