{"stem":"convey","instances":[{"docId":"amp-transcript__0043","docUri":"amp-transcript__0043.html","score":0.004309939520158866,"contexts":[{"form":"convey","weight":"1","pos":405,"context":"...visual,olfactory,auditory signals,b[]y which they <mark>convey<\/mark> to other members of their species vital information about...","fid":"text-resize-5"},{"form":"convey","weight":"1","pos":449,"context":".... What the poet or any artist has to <mark>convey<\/mark> is a perception of a reality common to all,but...","fid":"text-resize-5"}]},{"docId":"amp-transcript__0027","docUri":"amp-transcript__0027.html","score":0.004250718977133783,"contexts":[{"form":"convey","weight":"1","pos":398,"context":"...visual,olfactory,auditory signals,b[]y which they <mark>convey<\/mark> to other members of their species vital information about...","fid":"text-resize-3"},{"form":"convey","weight":"1","pos":442,"context":".... What the poet or any artist has to <mark>convey<\/mark> is a perception of a reality common to all,but...","fid":"text-resize-3"}]},{"docId":"amp-transcript__0062","docUri":"amp-transcript__0062.html","score":0.0004635732484220159,"contexts":[{"form":"convey","weight":"1","pos":4344,"context":"....  What the poet or any artist has to <mark>convey<\/mark> is a perception of a reality common to all,...","fid":"text-resize-61"}]}]}