{"stem":"critic","instances":[{"docId":"amp-transcript__0062","docUri":"amp-transcript__0062.html","score":0.003314708838733118,"contexts":[{"form":"criticisms","weight":"1","pos":1433,"context":"...correspondence 0279 and the newspapers, read and wrote <mark>criticisms<\/mark>, blacked each 0280 other's characters:  the Café...","fid":"text-resize-15"},{"form":"critic","weight":"1","pos":2024,"context":"...composer Paul Kont. 0399 A review by the <mark>critic<\/mark> Helmut A. Fiechtner in \"Die Furche\" 0400 gives the...","fid":"text-resize-21"},{"form":"critics","weight":"1","pos":3352,"context":"...rich collection 0658 of  dons, writers and <mark>critics<\/mark> from eastern and western Europe. 0659 A number...","fid":"text-resize-37"},{"form":"critic","weight":"1","pos":3411,"context":"...On the whole it was this leading West German <mark>critic<\/mark> with his 0668 maddeningly declamatory style and monitary ind...","fid":"text-resize-37"},{"form":"critic","weight":"1","pos":3596,"context":"...Mary MacCarthy, the Toynbees, the author and <mark>critic<\/mark> 0709 Hilde Spiel and a Danish journalist friend....","fid":"text-resize-39"},{"form":"criticism","weight":"1","pos":3663,"context":"...he said, 0722 built in a good deal of <mark>criticism<\/mark>, but could he get away with it? 0723...","fid":"text-resize-41"},{"form":"critics","weight":"1","pos":5744,"context":"...Stravinsky to which the young, 1180 whether artists or <mark>critics<\/mark> would do well to listen and ponder over. ","fid":"text-resize-63"},{"form":"critical","weight":"1","pos":6975,"context":"...:  it is one of a collection of 1439 <mark>critical<\/mark> essays edited by Monroe Spears and published in 1964...","fid":"text-resize-77"}]},{"docId":"amp-transcript__0028","docUri":"amp-transcript__0028.html","score":0.0020328288700892753,"contexts":[{"form":"criticism","weight":"1","pos":121,"context":"...lost.  Not 0026 for the first time self.-<mark>criticism<\/mark> was expressed, but while doubts 0027 concerning self-...","fid":"text-resize-1"},{"form":"criticism\"","weight":"1","pos":212,"context":"...:  \"It is not a work of literary 0046 <mark>criticism\"<\/mark>.  It may also be felt to lack an...","fid":"text-resize-3"}]},{"docId":"amp-transcript__0027","docUri":"amp-transcript__0027.html","score":0.0020873942766021967,"contexts":[{"form":"critics","weight":"1","pos":834,"context":"...to whcih which the young,wherewherewhether 0182 artists or <mark>critics<\/mark>,would do well to listen and pknde ponder over....","fid":"text-resize-5"}]},{"docId":"amp-transcript__0032","docUri":"amp-transcript__0032.html","score":0.01173387315249756,"contexts":[{"form":"critical","weight":"1","pos":155,"context":"...0039 in touch.  Incidentally I finished that <mark>critical<\/mark> book--to be published 0040 in the spring--after...","fid":"text-resize-1"}]},{"docId":"amp-transcript__0042","docUri":"amp-transcript__0042.html","score":0.008262602344883699,"contexts":[{"form":"critical","weight":"1","pos":174,"context":"...well tendered and observed by (vl) 0043loyal but <mark>critical<\/mark> eyes. (vl) 0044From the first,I think, (vl)...","fid":"text-resize-4"}]},{"docId":"amp-transcript__0043","docUri":"amp-transcript__0043.html","score":0.00220826788727404,"contexts":[{"form":"critics","weight":"1","pos":803,"context":"...to whcih which the young,wherewherewhether 0160 artists or <mark>critics<\/mark> would do well to listen and pknde ponder over....","fid":"text-resize-7"}]}]}