{"stem":"cut","instances":[{"docId":"amp-transcript__0028","docUri":"amp-transcript__0028.html","score":0.0022385896702042103,"contexts":[{"form":"cuttings","weight":"1","pos":82,"context":"...manuscripts, 0015 letters, personal notes and newspaper <mark>cuttings<\/mark>, and now we tried 0016 to winnow the...","fid":"text-resize-1"},{"form":"cuts","weight":"1","pos":776,"context":"...letter to Die Presse protesting sharply 0164 overagainst the <mark>cuts<\/mark> which had been made by the producer.  But...","fid":"text-resize-9"}]},{"docId":"amp-transcript__0062","docUri":"amp-transcript__0062.html","score":0.0009125550452504002,"contexts":[{"form":"cut","weight":"1","pos":4091,"context":"..., and lastly, taking drugs as a short <mark>cut<\/mark> to God 0815 is absolute drivel as well.' \"...","fid":"text-resize-45"},{"form":"cut","weight":"1","pos":7740,"context":"...to a meeting in Linz which I yearned to <mark>cut<\/mark>; 1608 particularly as I should like him to...","fid":"text-resize-87"}]},{"docId":"amp-transcript__0003","docUri":"amp-transcript__0003.html","score":0.02426382470315785,"contexts":[{"form":"cutting","weight":"1","pos":86,"context":"...the do after 7·30. 0034 I agree about the <mark>cutting<\/mark>. Will keep it till 0035 you come or...","fid":"text-resize-3"}]}]}