{"stem":"davon","instances":[{"docId":"amp-transcript__0039","docUri":"amp-transcript__0039.html","score":0.002995873797606873,"contexts":[{"form":"davon","weight":"1","pos":251,"context":"...wurde? Naturlich sorgte man dafür,dass nichts <mark>davon<\/mark> zu Ohren kam, ","fid":"text-resize-5"}]},{"docId":"amp-transcript__0052","docUri":"amp-transcript__0052.html","score":0.003153157171981234,"contexts":[{"form":"davon","weight":"1","pos":370,"context":"...sei,         zu seiner Muttersprache hegt , und zweitens <mark>davon<\/mark>, was         nach dem Krieg in den Ländern...","fid":"text-resize-3"}]},{"docId":"amp-transcript__0053","docUri":"amp-transcript__0053.html","score":0.0021896924805425233,"contexts":[{"form":"davon","weight":"1","pos":26,"context":"...Stimme zu hören, leider hattest Du nicht viel <mark>davon<\/mark>. Heute stehe ich immer noch unter dem Eindruck...","fid":"text-resize-1"}]},{"docId":"amp-transcript__0047","docUri":"amp-transcript__0047.html","score":0.0036243185884841777,"contexts":[{"form":"davon","weight":"1","pos":162,"context":"...?  Natürlich sorgte man dafür, daß nichts <mark>davon<\/mark> zu Ohren kam,      dass du unvorbereitet auf...","fid":"text-resize-1"}]}]}