{"stem":"decemb","instances":[{"docId":"amp-transcript__0062","docUri":"amp-transcript__0062.html","score":0.00067420538437962,"contexts":[{"form":"December","weight":"1","pos":2663,"context":"...the circumstances. 0496 Berlin-Dahlem, 23rd <mark>December<\/mark>, 1964: 0497 It was sweet of you...","fid":"text-resize-29"},{"form":"December","weight":"1","pos":4527,"context":"...Auden before and after 0867 Christmas 1968.  In <mark>December<\/mark>, Chester's Greek friend Jean Boras 0868 who often...","fid":"text-resize-51"}]},{"docId":"amp-transcript__0032","docUri":"amp-transcript__0032.html","score":0.009562205634554849,"contexts":[{"form":"December","weight":"1","pos":9,"context":" 1 <mark>December<\/mark> 1980 ","fid":"text-resize-1"}]}]}