{"stem":"depress","instances":[{"docId":"amp-transcript__0053","docUri":"amp-transcript__0053.html","score":0.004000317428193431,"contexts":[{"form":"depressive","weight":"1","pos":59,"context":"...0007 maßen zum Essen mitnahm. Diese manisch-<mark>depressive<\/mark> Genie,und 0008 dieser innerlich verschreckte Lausbub Friedrich...","fid":"text-resize-1"},{"form":"Depression","weight":"1","pos":627,"context":"...und langsam 0067 gefahren bin, aber inmitten dieser <mark>Depression<\/mark> war er immer wieder 0068 über die schöne Natur...","fid":"text-resize-2"}]},{"docId":"amp-transcript__0028","docUri":"amp-transcript__0028.html","score":0.000713536886217998,"contexts":[{"form":"depression","weight":"1","pos":620,"context":"...lof 1969 when Chester was sunk in deep 0130 <mark>depression<\/mark> while Wyśtan had a full work programme, and...","fid":"text-resize-7"}]},{"docId":"amp-transcript__0062","docUri":"amp-transcript__0062.html","score":0.00029062848956394854,"contexts":[{"form":"depressive","weight":"1","pos":1624,"context":"...drove out to lunch.  This manic- 0319 <mark>depressive<\/mark> genius Friedrich Heer, dieser verschreckter Lausbub, 0320...","fid":"text-resize-17"}]}]}