{"stem":"dri","instances":[{"docId":"amp-transcript__0018","docUri":"amp-transcript__0018.html","score":0.007970881961512626,"contexts":[{"form":"dry","weight":"1","pos":122,"context":"...or beer with.) But,no,we don't get a drop: <mark>dry<\/mark> you remain and doleful in a perpetual pique....","fid":"text-resize-4"}]},{"docId":"amp-transcript__0028","docUri":"amp-transcript__0028.html","score":0.0011728925408832395,"contexts":[{"form":"dried","weight":"1","pos":998,"context":"...brought with him.  There was a for example a <mark>dried<\/mark> leaf which, detected by me in a casserole,...","fid":"text-resize-15"}]}]}