{"stem":"eiermann","instances":[{"docId":"amp-transcript__0005","docUri":"amp-transcript__0005.html","score":0.05544806421603174,"contexts":[{"form":"Eiermann","weight":"1","pos":12,"context":" Death ofEmma <mark>Eiermann<\/mark> . ","fid":"text-resize-1"},{"form":"Eiermann","weight":"1","pos":31,"context":"...Dear Stella. A disaster has happened. Frau <mark>Eiermann<\/mark> died of a heart-attack on Nov 4th....","fid":"text-resize-3"}]},{"docId":"amp-transcript__0042","docUri":"amp-transcript__0042.html","score":0.008556800033338233,"contexts":[{"form":"Eiermann","weight":"1","pos":51,"context":" ELEGY (In Memoriam Emma <mark>Eiermann<\/mark>. ob ob.Nov 4th,I967) ","fid":"text-resize-4"}]},{"docId":"amp-transcript__0006","docUri":"amp-transcript__0006.html","score":0.03647898961581036,"contexts":[{"form":"Eiermanns","weight":"1","pos":36,"context":"...order to interview a prospective couple to take the <mark>Eiermanns<\/mark> place. Expect to be staying at the Hotel Königin...","fid":"text-resize-3"}]}]}