{"stem":"evid","instances":[{"docId":"amp-transcript__0062","docUri":"amp-transcript__0062.html","score":0.0015527939713513056,"contexts":[{"form":"evidently","weight":"1","pos":6786,"context":"...it was too much of an effort, and <mark>evidently<\/mark> the much 1398 older man felt the same way,...","fid":"text-resize-75"},{"form":"evidence","weight":"1","pos":6863,"context":"...Chester 1414 Kallman gave me his edxplanation for the <mark>evidence<\/mark> that Wystan had 1415 become older than his years...","fid":"text-resize-75"},{"form":"evident","weight":"1","pos":7928,"context":"...have it.  Knowing Austrian burial customs it was <mark>evident<\/mark> 1649 tthat we were faced with a cultural clash...","fid":"text-resize-89"}]},{"docId":"amp-transcript__0028","docUri":"amp-transcript__0028.html","score":0.0012689242379930446,"contexts":[{"form":"evidence","weight":"1","pos":521,"context":"...known:  from that time on - 0109 there is <mark>evidence<\/mark> in the poetry - sex and love became, for...","fid":"text-resize-5"}]}]}