{"stem":"fee","instances":[{"docId":"amp-transcript__0062","docUri":"amp-transcript__0062.html","score":0.0012449095702504005,"contexts":[{"form":"fee","weight":"1","pos":1755,"context":"...poetry on his lists showed idealism enough.  A translation <mark>fee<\/mark> usually wiped out any conceivable profits on literqary prose...","fid":"text-resize-23"},{"form":"fees","weight":"1","pos":5724,"context":"...school nearby, the family couldn't acfford boarding school <mark>fees<\/mark>, nor lodgings.  Not long after this chance...","fid":"text-resize-81"}]}]}