{"stem":"fill","instances":[{"docId":"amp-transcript__0062","docUri":"amp-transcript__0062.html","score":0.0029016159866164966,"contexts":[{"form":"filling","weight":"1","pos":598,"context":"...she spent her summers until she 0114 died, <mark>filling<\/mark> the house with her friends, often like herself...","fid":"text-resize-7"},{"form":"filled","weight":"1","pos":1238,"context":"...the kaimak hissing faintly as the cup 0240 is <mark>filled<\/mark> - that pale brown foam which must be removed...","fid":"text-resize-13"},{"form":"filled","weight":"1","pos":1257,"context":"...unforgiveable sin.   And Auden would sit, 0243 <mark>filled<\/mark> with well nourished, blinking in the sunshine from...","fid":"text-resize-13"},{"form":"filled","weight":"1","pos":4940,"context":"...swhich he gave me, the blank pages are 1001 <mark>filled<\/mark> with his notes - and even a new 12...","fid":"text-resize-55"},{"form":"filled","weight":"1","pos":7075,"context":"...in the early autumn 1460 of 1968 Vienna was <mark>filled<\/mark> with people who had come across the 1461 border...","fid":"text-resize-79"}]}]}