{"stem":"johnston","instances":[{"docId":"amp-transcript__0043","docUri":"amp-transcript__0043.html","score":0.0027656874131056735,"contexts":[{"form":"Johnston","weight":"1","pos":1167,"context":"...,they can do two things. 0226 They can,as Dr <mark>Johnston<\/mark> said,'enable us a little better to enjoy life...","fid":"text-resize-9"}]},{"docId":"amp-transcript__0027","docUri":"amp-transcript__0027.html","score":0.0026115534142680287,"contexts":[{"form":"Johnston","weight":"1","pos":1220,"context":"...,they can do two things. 0261 They can,as Dr <mark>Johnston<\/mark> said,'enable us a little better to enjoy life...","fid":"text-resize-7"}]}]}