{"stem":"mescalin","instances":[{"docId":"amp-transcript__0029","docUri":"amp-transcript__0029.html","score":0.018129499700196474,"contexts":[{"form":"mescalin","weight":"1","pos":72,"context":"...length about 0022 his [] trials of LSD &amp;<mark>mescalin<\/mark>, 0023 Point is that young people need 0024...","fid":"text-resize-1"},{"form":"mescalin","weight":"1","pos":112,"context":"...lot of harm by publishing 0035 his experiences with <mark>mescalin<\/mark>, 0036 making people think it is 0037 an...","fid":"text-resize-2"}]},{"docId":"amp-transcript__0062","docUri":"amp-transcript__0062.html","score":0.0003371026921898092,"contexts":[{"form":"mescalin","weight":"1","pos":3790,"context":"...a lot of harm by publishing his experiences with <mark>mescalin<\/mark>, and 0710 making people believe it to be...","fid":"text-resize-43"}]}]}