{"stem":"month","instances":[{"docId":"amp-transcript__0028","docUri":"amp-transcript__0028.html","score":0.004730899103871273,"contexts":[{"form":"months","weight":"1","pos":108,"context":"...is often said, but with 0022 interruptions for five <mark>months<\/mark>, depending on his engagements. 0023 In the...","fid":"text-resize-1"},{"form":"months","weight":"1","pos":448,"context":"... By one of them he was robbed of three <mark>months<\/mark>´ income 0094 in succession.  Or else he...","fid":"text-resize-5"},{"form":"months","weight":"1","pos":1653,"context":"...course of one year I always stay under six <mark>months<\/mark> in Austrisaaa 0376 and never spend more than three...","fid":"text-resize-21"},{"form":"months","weight":"1","pos":1657,"context":"...in Austrisaaa 0376 and never spend more than three <mark>months<\/mark> here consecutively. 0377      A word in conclusion:...","fid":"text-resize-21"}]},{"docId":"amp-transcript__0062","docUri":"amp-transcript__0062.html","score":0.0009640676991490339,"contexts":[{"form":"months","weight":"1","pos":1641,"context":"...a man 0322 let out of prison.  For <mark>months<\/mark> at a time he never escapes from the 0323...","fid":"text-resize-17"},{"form":"monthly","weight":"1","pos":2908,"context":".... 0578 It was very ungrateful to accept a <mark>monthly<\/mark> grant of a couple 0579 of tohousand marks and...","fid":"text-resize-31"}]},{"docId":"amp-transcript__0032","docUri":"amp-transcript__0032.html","score":0.013653822709545639,"contexts":[{"form":"month","weight":"1","pos":16,"context":" 0006 I just got back from a <mark>month<\/mark> in England to find your letter. I was...","fid":"text-resize-1"}]}]}