{"stem":"poor","instances":[{"docId":"amp-transcript__0004","docUri":"amp-transcript__0004.html","score":0.007565817744626706,"contexts":[{"form":"poor","weight":"1","pos":123,"context":"...rich could hire other people to die for them,the <mark>poor<\/mark> 0029      couold make a wonderful living\", or...","fid":"text-resize-3"}]},{"docId":"amp-transcript__0018","docUri":"amp-transcript__0018.html","score":0.006415255599130479,"contexts":[{"form":"poor","weight":"1","pos":176,"context":"...Who or what are you mad at? What has <mark>poor<\/mark> Austria done to draw such disapproval? The Beamterei...","fid":"text-resize-4"}]},{"docId":"amp-transcript__0062","docUri":"amp-transcript__0062.html","score":0.0002992498849981323,"contexts":[{"form":"poor","weight":"1","pos":6541,"context":"...hire other people 1271 to die for them, the <mark>poor<\/mark> could make a wonderful living', or, ","fid":"text-resize-73"}]}]}