{"stem":"quotat","instances":[{"docId":"amp-transcript__0038","docUri":"amp-transcript__0038.html","score":0.009019015860519671,"contexts":[{"form":"Quotation","weight":"1","pos":261,"context":" 0018                        ___ 0019 N  I) <mark>Quotation<\/mark> from W8's poem Auf das Unabwendbare. 0020    2)...","fid":"text-resize-7"},{"form":"Quotation","weight":"1","pos":267,"context":"...from W8's poem Auf das Unabwendbare. 0020    2) <mark>Quotation<\/mark> from W's poem Kammermusik. 0021                         __ ","fid":"text-resize-7"}]},{"docId":"amp-transcript__0031","docUri":"amp-transcript__0031.html","score":0.003299926376049515,"contexts":[{"form":"quotation","weight":"1","pos":332,"context":"...idea is absurd and 0079 the point of my <mark>quotation<\/mark> in my talk in 1976 was to show Auden...","fid":"text-resize-3"}]},{"docId":"amp-transcript__0028","docUri":"amp-transcript__0028.html","score":0.0006494985793967268,"contexts":[{"form":"quotation","weight":"1","pos":2676,"context":"...literally.\" 0591      \"Who would know where that familiar <mark>quotation<\/mark> comes from?\" 0592 I wondered. 0593      \"I would\"...","fid":"text-resize-33"}]},{"docId":"amp-transcript__0062","docUri":"amp-transcript__0062.html","score":0.0002645452460131552,"contexts":[{"form":"quotation","weight":"1","pos":6938,"context":"...: 1440 the operative phrase lies buried in the <mark>quotation<\/mark>. ","fid":"text-resize-77"}]}]}