{"stem":"relat","instances":[{"docId":"amp-transcript__0062","docUri":"amp-transcript__0062.html","score":0.0005031219756642125,"contexts":[{"form":"relation","weight":"1","pos":2222,"context":"...on Austria Auden was to write: 0418     \"The <mark>relation<\/mark> between Art and Societsy is so obscure that only...","fid":"text-resize-23"},{"form":"relation","weight":"1","pos":6529,"context":"...the contradictions of human 1269 existence, and the <mark>relation<\/mark> between man and God, occasions for 1270 humorous...","fid":"text-resize-73"}]},{"docId":"amp-transcript__0004","docUri":"amp-transcript__0004.html","score":0.006360118018450856,"contexts":[{"form":"relation","weight":"1","pos":112,"context":"...suffering,and the contradictions of human existence,and the <mark>relation<\/mark> 0027       between man and God,occasions for humorous...","fid":"text-resize-3"}]},{"docId":"amp-transcript__0031","docUri":"amp-transcript__0031.html","score":0.0030715530587794165,"contexts":[{"form":"relations","weight":"1","pos":425,"context":"...pretty well under control these days. My 0099 <mark>relations<\/mark> organised a splendid surprise party for my 70th 0100...","fid":"text-resize-3"}]},{"docId":"amp-transcript__0041","docUri":"amp-transcript__0041.html","score":0.010356298366327057,"contexts":[{"form":"relation","weight":"1","pos":82,"context":"...it be translated? 0024 As you say, the <mark>relation<\/mark> betwen art and society 0025 is very odd....","fid":"text-resize-3"}]},{"docId":"amp-transcript__0028","docUri":"amp-transcript__0028.html","score":0.0006152795559384632,"contexts":[{"form":"relations","weight":"1","pos":2376,"context":"....  Once everyone had agreed 0494 that Auden´s <mark>relations<\/mark> must be told immediately that the funeral 0495 ahhad...","fid":"text-resize-29"}]}]}