{"stem":"seiner","instances":[{"docId":"amp-transcript__0053","docUri":"amp-transcript__0053.html","score":0.0022629173507460244,"contexts":[{"form":"seiner","weight":"1","pos":700,"context":"...in den seelischen 0073 Entbehrungen, die die Scheidung <mark>seiner<\/mark> Eltern verursachte. 0074 Ärgerst Du Dich schon darüber...","fid":"text-resize-2"}]},{"docId":"amp-transcript__0052","docUri":"amp-transcript__0052.html","score":0.0031680842910444345,"contexts":[{"form":"seiner","weight":"1","pos":411,"context":"...von welcher Nationalität er auch sei, 0046         zu <mark>seiner<\/mark> Muttersprache hegt , und zweitens davon, was 0047...","fid":"text-resize-3"}]}]}