{"stem":"sonst","instances":[{"docId":"amp-transcript__0053","docUri":"amp-transcript__0053.html","score":0.0022629173507460244,"contexts":[{"form":"sonst","weight":"1","pos":958,"context":"...es\". 0100 Jetzt will ich Deine Fragen beantworten und <mark>sonst<\/mark> noch schauen 0101 was in Deinem letzten Brief steht...","fid":"text-resize-2"}]},{"docId":"amp-transcript__0052","docUri":"amp-transcript__0052.html","score":0.0031680842910444345,"contexts":[{"form":"sonst","weight":"1","pos":124,"context":"...ein 'persönliches' Interesse an Öster- 0015 reich, <mark>sonst<\/mark> käme ich nicht hierher. Mir gefällt die Landschaft...","fid":"text-resize-1"}]}]}