{"stem":"spiel","instances":[{"docId":"amp-transcript__0051","docUri":"amp-transcript__0051.html","score":0.006878077737135944,"contexts":[{"form":"Spiel","weight":"1","pos":73,"context":"...obwohl, oder gerade weil es hier um ein <mark>Spiel<\/mark> ging , nicht eine Notwendigkeit wie essen oder schlafen...","fid":"text-resize-1"}]},{"docId":"amp-transcript__0062","docUri":"amp-transcript__0062.html","score":0.0005222116963260056,"contexts":[{"form":"Spiel","weight":"1","pos":2848,"context":"..., the Toynbees, the author and critic Hilde <mark>Spiel<\/mark> and a Danish journalist friend.  But over drink...","fid":"text-resize-39"}]}]}