{"stem":"uin","instances":[{"docId":"amp-transcript__0053","docUri":"amp-transcript__0053.html","score":0.0022629173507460244,"contexts":[{"form":"uin","weight":"1","pos":858,"context":"...enorm, und gleich krie kreisten seine Gedanken 0089 <mark>uin<\/mark> weiß Gott was für Konvolutionen. Ach ja, jetzt...","fid":"text-resize-2"}]},{"docId":"amp-transcript__0062","docUri":"amp-transcript__0062.html","score":0.0003371026921898092,"contexts":[{"form":"uin","weight":"1","pos":2377,"context":"...play is read in English or German.  And <mark>uin<\/mark> a way, 0448 Eliot hardly deserved it:  Not longo...","fid":"text-resize-25"}]}]}