{"stem":"willkommen","instances":[{"docId":"amp-transcript__0047","docUri":"amp-transcript__0047.html","score":0.006010671909527499,"contexts":[{"form":"willkommen","weight":"1","pos":375,"context":"...für Folterer, (In welchen Bars sind 0042 sie <mark>willkommen<\/mark>?  WelcheMädchen heiraten sie?) 0043      noch...","fid":"text-resize-1"}]},{"docId":"amp-transcript__0039","docUri":"amp-transcript__0039.html","score":0.004799218656444439,"contexts":[{"form":"willkommen","weight":"1","pos":520,"context":"...0070 Stellungen für Folterer,(In welchen Bars sind sie <mark>willkommen<\/mark>? Welche Mädchen 0071 heiraten sie?) ","fid":"text-resize-5"}]}]}